{
  "type": "Feature",
  "properties": {
    "gn:admin1_code":"8.0",
    "gn:asciiname":"Scotts Head Village",
    "gn:cc2":"DM",
    "gn:country_code":"DM",
    "gn:dem":61,
    "gn:feature_class":"P",
    "gn:feature_code":"PPL",
    "gn:name":"Scotts Head Village",
    "gn:population":0,
    "gn:timezone":"America/Dominica",
    "iso:country":"DM",
    "name:deu_x_preferred":[
        "Scotts Head"
    ],
    "name:ell_x_preferred":[
        "\u03a3\u03ba\u03bf\u03c4\u03c2 \u03a7\u03b5\u03bd\u03c4"
    ],
    "name:fin_x_preferred":[
        "Scotts Head"
    ],
    "name:fra_x_preferred":[
        "Scotts Head"
    ],
    "name:lit_x_preferred":[
        "Skots Hydas"
    ],
    "name:pol_x_preferred":[
        "Scotts Head"
    ],
    "name:ron_x_preferred":[
        "Scotts Head"
    ],
    "name:und_x_variant":[
        "Cachacrou",
        "Scotts Head Village"
    ],
    "name:zho_x_preferred":[
        "\u65af\u79d1\u8328\u89d2"
    ],
    "wof:name":"Scotts Head Village",
    "wof:placetype":"locality"
},
  "geometry": {"coordinates":[-61.36482,15.21222],"type":"Point"}
}