{
  "type": "Feature",
  "properties": {
    "gn:admin1_code":"5.0",
    "gn:asciiname":"La Haut",
    "gn:country_code":"DM",
    "gn:dem":219,
    "gn:feature_class":"P",
    "gn:feature_code":"PPL",
    "gn:name":"L\u00e0 Haut",
    "gn:population":0,
    "gn:timezone":"America/Dominica",
    "iso:country":"DM",
    "wof:name":"La Haut",
    "wof:placetype":"locality"
},
  "geometry": {"coordinates":[-61.41628000000001,15.62603],"type":"Point"}
}