{
  "type": "Feature",
  "properties": {
    "gn:admin1_code":"6.0",
    "gn:asciiname":"Riversdale",
    "gn:country_code":"DM",
    "gn:dem":395,
    "gn:feature_class":"P",
    "gn:feature_code":"PPL",
    "gn:name":"Riversdale",
    "gn:population":0,
    "gn:timezone":"America/Dominica",
    "iso:country":"DM",
    "wof:name":"Riversdale",
    "wof:placetype":"locality"
},
  "geometry": {"coordinates":[-61.36666999999999,15.41667],"type":"Point"}
}