{
  "type": "Feature",
  "properties": {
    "gn:admin1_code":"10.0",
    "gn:asciiname":"Tarou",
    "gn:country_code":"DM",
    "gn:dem":-9999,
    "gn:feature_class":"P",
    "gn:feature_code":"PPL",
    "gn:name":"Tarou",
    "gn:population":0,
    "gn:timezone":"America/Dominica",
    "iso:country":"DM",
    "wof:name":"Tarou",
    "wof:placetype":"locality"
},
  "geometry": {"coordinates":[-61.41667,15.38333],"type":"Point"}
}