{
  "type": "Feature",
  "properties": {
    "gn:country":"DM",
    "gn:fcode":"PPLA",
    "gn:population":1202,
    "iso:country":"DM",
    "name:ceb_x_preferred":[
        "Pointe Michel"
    ],
    "name:deu_x_preferred":[
        "Pointe Michel"
    ],
    "name:ell_x_preferred":[
        "\u03a0\u03bf\u03c5\u03ac\u03bd\u03c4 \u039c\u03b9\u03c3\u03ad\u03bb"
    ],
    "name:eng_x_preferred":[
        "Pointe Michel"
    ],
    "name:fin_x_preferred":[
        "Pointe Michel"
    ],
    "name:fra_x_preferred":[
        "Pointe-Michel"
    ],
    "name:heb_x_preferred":[
        "\u05e4\u05d5\u05d9\u05e0\u05d8 \u05de\u05d9\u05e9\u05dc"
    ],
    "name:jpn_x_preferred":[
        "\u30dd\u30ef\u30f3\u30c8\u30fb\u30de\u30a4\u30b1\u30eb"
    ],
    "name:nld_x_preferred":[
        "Pointe Michel"
    ],
    "name:pol_x_preferred":[
        "Pointe Michel"
    ],
    "name:por_x_preferred":[
        "Pointe Michel"
    ],
    "name:ron_x_preferred":[
        "Pointe Michel"
    ],
    "name:spa_x_preferred":[
        "Pointe Michel"
    ],
    "name:swe_x_preferred":[
        "Pointe Michel"
    ],
    "name:ukr_x_preferred":[
        "\u041f\u043e\u0439\u043d\u0442-\u041c\u0456\u0448\u0435\u043b\u044c"
    ],
    "name:und_x_variant":[
        "La Pointe"
    ],
    "name:zho_x_preferred":[
        "\u7c73\u6b47\u723e\u89d2"
    ],
    "qs:name":"Pointe Michel",
    "qs:photos_9r":0,
    "qs:photos_sr":0,
    "qs:pop_sr":"3",
    "wd:wordcount":59,
    "wof:name":"Pointe Michel",
    "wof:placetype":"locality",
    "wof:population":1202
},
  "geometry": {"coordinates":[-61.38333,15.25],"type":"Point"}
}