{
  "type": "Feature",
  "properties": {
    "gn:admin1_code":"2.0",
    "gn:asciiname":"Tobino",
    "gn:country_code":"DM",
    "gn:dem":-9999,
    "gn:feature_class":"P",
    "gn:feature_code":"PPL",
    "gn:name":"Tobino",
    "gn:population":0,
    "gn:timezone":"America/Dominica",
    "iso:country":"DM",
    "wof:name":"Tobino",
    "wof:placetype":"locality"
},
  "geometry": {"coordinates":[-61.40592,15.61435],"type":"Point"}
}