{
  "type": "Feature",
  "properties": {
    "gn:asciiname":"Capuchin",
    "gn:country_code":"DM",
    "gn:dem":95,
    "gn:feature_class":"P",
    "gn:feature_code":"PPL",
    "gn:name":"Capuchin",
    "gn:population":0,
    "gn:timezone":"America/Dominica",
    "iso:country":"DM",
    "wof:name":"Capuchin",
    "wof:placetype":"locality"
},
  "geometry": {"coordinates":[-61.46033000000001,15.6315],"type":"Point"}
}