{
  "type": "Feature",
  "properties": {
    "gn:asciiname":"Capuchin",
    "gn:country_code":"DM",
    "gn:dem":95,
    "gn:feature_class":"P",
    "gn:feature_code":"PPL",
    "gn:name":"Capuchin",
    "gn:population":0,
    "gn:timezone":"America/Dominica",
    "iso:country":"DM",
    "name:eus_x_preferred":[
        "Kaputxino"
    ],
    "name:fra_x_preferred":[
        "Capucine"
    ],
    "name:rus_x_preferred":[
        "\u041a\u0430\u043f\u0443\u0446\u0438\u043d"
    ],
    "name:spa_x_preferred":[
        "Capuchino"
    ],
    "name:ukr_x_preferred":[
        "\u041a\u0430\u043f\u0443\u0446\u0438\u043d\u0438"
    ],
    "wof:name":"Capuchin",
    "wof:placetype":"locality"
},
  "geometry": {"coordinates":[-61.46033000000001,15.6315],"type":"Point"}
}