{
  "type": "Feature",
  "properties": {
    "gn:admin1_code":"5.0",
    "gn:asciiname":"Glanvillia",
    "gn:country_code":"DM",
    "gn:dem":1,
    "gn:feature_class":"P",
    "gn:feature_code":"PPL",
    "gn:name":"Glanvillia",
    "gn:population":0,
    "gn:timezone":"America/Dominica",
    "iso:country":"DM",
    "name:und_x_variant":[
        "Glanville",
        "Glanvillia"
    ],
    "wof:name":"Glanvillia",
    "wof:placetype":"locality"
},
  "geometry": {"coordinates":[-61.45591999999999,15.5696],"type":"Point"}
}