{
  "type": "Feature",
  "properties": {
    "gn:asciiname":"Canefield",
    "gn:country_code":"DM",
    "gn:dem":19,
    "gn:feature_class":"P",
    "gn:feature_code":"PPL",
    "gn:name":"Canefield",
    "gn:population":0,
    "gn:timezone":"America/Dominica",
    "iso:country":"DM",
    "wof:name":"Canefield",
    "wof:placetype":"locality"
},
  "geometry": {"coordinates":[-61.38916,15.33137],"type":"Point"}
}