{
  "type": "Feature",
  "properties": {
    "gn:asciiname":"Canefield",
    "gn:country_code":"DM",
    "gn:dem":19,
    "gn:feature_class":"P",
    "gn:feature_code":"PPL",
    "gn:name":"Canefield",
    "gn:population":0,
    "gn:timezone":"America/Dominica",
    "iso:country":"DM",
    "name:ceb_x_preferred":[
        "Canefield"
    ],
    "name:fra_x_preferred":[
        "Canefield"
    ],
    "name:pol_x_preferred":[
        "Canefield"
    ],
    "name:por_x_preferred":[
        "Canefield"
    ],
    "name:ron_x_preferred":[
        "Canefield"
    ],
    "name:spa_x_preferred":[
        "Canefield"
    ],
    "name:swe_x_preferred":[
        "Canefield"
    ],
    "name:zho_x_preferred":[
        "\u574e\u83f2\u723e\u5fb7"
    ],
    "wof:name":"Canefield",
    "wof:placetype":"locality"
},
  "geometry": {"coordinates":[-61.38916,15.33137],"type":"Point"}
}