{
  "type": "Feature",
  "properties": {
    "gn:admin1_code":"9.0",
    "gn:asciiname":"Tete Morne",
    "gn:country_code":"DM",
    "gn:dem":1,
    "gn:feature_class":"P",
    "gn:feature_code":"PPL",
    "gn:name":"T\u00eate Morne",
    "gn:population":0,
    "gn:timezone":"America/Dominica",
    "iso:country":"DM",
    "name:und_x_variant":[
        "T\u00eate Morne",
        "Tete Morne"
    ],
    "wof:name":"Tete Morne",
    "wof:placetype":"locality"
},
  "geometry": {"coordinates":[-61.33384,15.23554],"type":"Point"}
}