{
  "type": "Feature",
  "properties": {
    "gn:admin1_code":"2.0",
    "gn:asciiname":"Paix Bouche",
    "gn:country_code":"DM",
    "gn:dem":1,
    "gn:feature_class":"P",
    "gn:feature_code":"PPL",
    "gn:name":"Paix Bouche",
    "gn:population":0,
    "gn:timezone":"America/Dominica",
    "iso:country":"DM",
    "name:ceb_x_preferred":[
        "Paix Bouche"
    ],
    "name:ell_x_preferred":[
        "\u03a0\u03b1\u03b9 \u039c\u03c0\u03bf\u03c5\u03c2"
    ],
    "name:fas_x_preferred":[
        "\u067e\u0647 \u067e\u0648\u0634"
    ],
    "name:pol_x_preferred":[
        "Paix Bouche"
    ],
    "name:ron_x_preferred":[
        "Paix Bouche"
    ],
    "name:swe_x_preferred":[
        "Paix Bouche"
    ],
    "wof:name":"Paix Bouche",
    "wof:placetype":"locality"
},
  "geometry": {"coordinates":[-61.41133000000001,15.59248],"type":"Point"}
}