{
  "type": "Feature",
  "properties": {
    "gn:country":"DM",
    "gn:fcode":"PPL",
    "gn:pop":1387,
    "iso:country":"DM",
    "name:deu_x_preferred":[
        "Castle Bruce"
    ],
    "name:ell_x_preferred":[
        "\u039a\u03b1\u03c3\u03bb \u039c\u03c0\u03c1\u03bf\u03c5\u03c2"
    ],
    "name:eng_x_preferred":[
        "Castle Bruce"
    ],
    "name:fas_x_preferred":[
        "\u06a9\u0627\u0633\u062a\u0644 \u0628\u0631\u0648\u0633"
    ],
    "name:fra_x_preferred":[
        "Castle-Bruce"
    ],
    "name:nld_x_preferred":[
        "Castle Bruce"
    ],
    "name:pol_x_preferred":[
        "Castle Bruce"
    ],
    "name:por_x_preferred":[
        "Castle Bruce"
    ],
    "name:ron_x_preferred":[
        "Castle Bruce"
    ],
    "name:spa_x_preferred":[
        "Castle Bruce"
    ],
    "name:swe_x_preferred":[
        "Castle Bruce"
    ],
    "qs:name":"Castle Bruce",
    "qs:photos_9r":0,
    "qs:photos_sr":0,
    "qs:pop_sr":"3",
    "wd:wordcount":88,
    "wof:name":"Castle Bruce",
    "wof:placetype":"locality",
    "wof:population":1387
},
  "geometry": {"coordinates":[-61.26667,15.43333],"type":"Point"}
}