{
  "type": "Feature",
  "properties": {
    "gn:country":"DM",
    "gn:fcode":"PPL",
    "gn:population":1387,
    "iso:country":"DM",
    "name:ast_x_preferred":[
        "Castle Bruce"
    ],
    "name:ceb_x_preferred":[
        "Castle Bruce"
    ],
    "name:deu_x_preferred":[
        "Castle Bruce"
    ],
    "name:ell_x_preferred":[
        "\u039a\u03b1\u03c3\u03bb \u039c\u03c0\u03c1\u03bf\u03c5\u03c2"
    ],
    "name:eng_x_preferred":[
        "Castle Bruce"
    ],
    "name:fas_x_preferred":[
        "\u06a9\u0627\u0633\u062a\u0644 \u0628\u0631\u0648\u0633"
    ],
    "name:fra_x_preferred":[
        "Castle-Bruce"
    ],
    "name:jpn_x_preferred":[
        "\u30ab\u30c3\u30b9\u30eb\u30fb\u30d6\u30eb\u30fc\u30b9"
    ],
    "name:nld_x_preferred":[
        "Castle Bruce"
    ],
    "name:pol_x_preferred":[
        "Castle Bruce"
    ],
    "name:por_x_preferred":[
        "Castle Bruce"
    ],
    "name:ron_x_preferred":[
        "Castle Bruce"
    ],
    "name:rus_x_preferred":[
        "\u041a\u0430\u0441\u043b-\u0411\u0440\u044e\u0441"
    ],
    "name:spa_x_preferred":[
        "Castle Bruce"
    ],
    "name:swe_x_preferred":[
        "Castle Bruce"
    ],
    "name:tha_x_preferred":[
        "\u0e04\u0e32\u0e2a\u0e40\u0e0b\u0e34\u0e25\u0e1a\u0e23\u0e39\u0e0b"
    ],
    "name:zho_x_preferred":[
        "\u5361\u65af\u723e\u5e03\u9b6f\u65af"
    ],
    "qs:name":"Castle Bruce",
    "qs:photos_9r":0,
    "qs:photos_sr":0,
    "qs:pop_sr":"3",
    "wd:wordcount":88,
    "wof:name":"Castle Bruce",
    "wof:placetype":"locality",
    "wof:population":1387
},
  "geometry": {"coordinates":[-61.26667,15.43333],"type":"Point"}
}