{
  "type": "Feature",
  "properties": {
    "gn:admin1_code":"5.0",
    "gn:asciiname":"Tanetane",
    "gn:country_code":"DM",
    "gn:dem":1,
    "gn:feature_class":"P",
    "gn:feature_code":"PPL",
    "gn:name":"Tanetane",
    "gn:population":0,
    "gn:timezone":"America/Dominica",
    "iso:country":"DM",
    "wof:name":"Tanetane",
    "wof:placetype":"locality"
},
  "geometry": {"coordinates":[-61.46111,15.60188],"type":"Point"}
}