{
  "type": "Feature",
  "properties": {
    "gn:admin1_code":"2.0",
    "gn:asciiname":"Gommier",
    "gn:country_code":"DM",
    "gn:dem":-9999,
    "gn:feature_class":"P",
    "gn:feature_code":"PPL",
    "gn:name":"Gommier",
    "gn:population":0,
    "gn:timezone":"America/Dominica",
    "iso:country":"DM",
    "wof:name":"Gommier",
    "wof:placetype":"locality"
},
  "geometry": {"coordinates":[-61.40347,15.6097],"type":"Point"}
}